pyAyiin/__init__.py
pyAyiin/__main__.py
pyAyiin/config.py
pyAyiin/connection.py
pyAyiin/decorator.py
pyAyiin/exception.py
pyAyiin/storage.py
pyAyiin/utils.py
pyAyiin/database/__init__.py
pyAyiin/database/_core.py
pyAyiin/database/blFilters.py
pyAyiin/database/blGcast.py
pyAyiin/database/botBlacklist.py
pyAyiin/database/botPms.py
pyAyiin/database/botStart.py
pyAyiin/database/broadcast.py
pyAyiin/database/filters.py
pyAyiin/database/gban.py
pyAyiin/database/handler.py
pyAyiin/database/log.py
pyAyiin/database/muted.py
pyAyiin/database/notes.py
pyAyiin/database/permit.py
pyAyiin/database/sudo.py
pyAyiin/database/sudoHandler.py
pyAyiin/database/variable.py
pyAyiin/dist/index.js
pyAyiin/dist/index.js.map
pyAyiin/lib/FastTelethon.py
pyAyiin/lib/__init__.py
pyAyiin/lib/aihelp.py
pyAyiin/lib/chrome.py
pyAyiin/lib/converter.py
pyAyiin/lib/events.py
pyAyiin/lib/format.py
pyAyiin/lib/googleImages.py
pyAyiin/lib/misc.py
pyAyiin/lib/myHeroku.py
pyAyiin/lib/paste.py
pyAyiin/lib/pasteBin.py
pyAyiin/lib/pretyJson.py
pyAyiin/lib/progres.py
pyAyiin/lib/queues.py
pyAyiin/lib/thumbnail.py
pyAyiin/lib/tools.py
pyAyiin/lib/truthDare.py
pyAyiin/lib/utils.py
pyAyiin/node_modules/.package-lock.json
pyAyiin/node_modules/.bin/acorn
pyAyiin/node_modules/.bin/ts-node
pyAyiin/node_modules/.bin/ts-node-cwd
pyAyiin/node_modules/.bin/ts-node-esm
pyAyiin/node_modules/.bin/ts-node-script
pyAyiin/node_modules/.bin/ts-node-transpile-only
pyAyiin/node_modules/.bin/ts-script
pyAyiin/node_modules/.bin/tsc
pyAyiin/node_modules/.bin/tsserver
pyAyiin/node_modules/@cspotcode/source-map-support/LICENSE.md
pyAyiin/node_modules/@cspotcode/source-map-support/README.md
pyAyiin/node_modules/@cspotcode/source-map-support/browser-source-map-support.js
pyAyiin/node_modules/@cspotcode/source-map-support/package.json
pyAyiin/node_modules/@cspotcode/source-map-support/register-hook-require.d.ts
pyAyiin/node_modules/@cspotcode/source-map-support/register-hook-require.js
py_Ayiin-0.6.0.dist-info/LICENSE
py_Ayiin-0.6.0.dist-info/METADATA
py_Ayiin-0.6.0.dist-info/NOTICE
py_Ayiin-0.6.0.dist-info/WHEEL
py_Ayiin-0.6.0.dist-info/top_level.txt
py_Ayiin-0.6.0.dist-info/RECORD
