Metadata-Version: 2.1
Name: py-Ayiin
Version: 0.6.0
Summary: A Secure and Powerful Python-Telethon Based and Python-Pyrogram Based Library For Your Userbot Module.
Home-page: https://github.com/AyiinXd/AyiinXd
Author: AyiinXd
Author-email: ayingaming98@gmail.com
License: GNU General Public License v3.0 (GPL-3.0)
Project-URL: Bug Tracker, https://github.com/AyiinXd/AyiinXd/issues
Project-URL: Source Code, https://github.com/AyiinXd/AyiinXd
Platform: UNKNOWN
Classifier: Programming Language :: Python :: 3
Classifier: Programming Language :: Python :: 3.8
Classifier: Programming Language :: Python :: 3.9
Classifier: Programming Language :: Python :: 3.10
Classifier: Programming Language :: Python :: 3.11
Classifier: License :: OSI Approved :: GNU General Public License v3 (GPLv3)
Classifier: Operating System :: OS Independent
Requires-Python: ~=3.7
Requires-Dist: aiofiles
Requires-Dist: aiohttp[speedups]
Requires-Dist: beautifulsoup4
Requires-Dist: bs4
Requires-Dist: dnspython
Requires-Dist: emoji==1.7.0
Requires-Dist: hachoir
Requires-Dist: html-telegraph-poster
Requires-Dist: markdown
Requires-Dist: openai
Requires-Dist: pillow
Requires-Dist: pybase64
Requires-Dist: python-dotenv
Requires-Dist: requests
Requires-Dist: selenium
Requires-Dist: setuptools
Requires-Dist: telethon
Requires-Dist: telethon-session-sqlalchemy
Requires-Dist: telethon-tgcrypto
Requires-Dist: py-tgcalls
Requires-Dist: yt-dlp
